{
  "url": "https://cc.musabi.ac.jp/campus-2nd/campus-life",
  "title": "学生生活 - 在学生の方（学2課程）",
  "content": [
    {
      "type": "heading",
      "level": 1,
      "text": "学生生活"
    },
    {
      "type": "heading",
      "level": 2,
      "text": "学生生活の支援"
    },
    {
      "type": "paragraph",
      "text": "自宅で自由に学習できることが通信教育の最大の利点ですが、さまざまな活動やツールを通して、学生同士、大学と学生、教員と学生の交流の機会も多く、豊かで刺激的な学生生活を送ることができます。提携している美術館・博物館に入館できる「キャンパスメンバーズ」、奨学金制度など学生支援体制も充実しているので、大いに利用してください。"
    },
    {
      "type": "heading",
      "level": 2,
      "text": "奨学金"
    },
    {
      "type": "heading",
      "level": 3,
      "text": "奨学金の種類と内容"
    },
    {
      "type": "paragraph",
      "text": "奨学金制度は、経済的に安定した学生生活を送るために設けられています。奨学金を受けるためには、学力・人物ともに優れ、経済的に修学が困難であると認められることが条件となります。"
    },
    {
      "type": "heading",
      "level": 4,
      "text": "武蔵野美術大学造形学部通信教育課程奨励奨学金"
    },
    {
      "type": "paragraph",
      "text": "優秀で意欲のある学生を経済的に援助し、さらに有意義な教育環境を創造するために設けられた本学通信教育課程独自の奨学金制度です。奨学金の贈与を受ける者を奨学生と呼び、「第1種奨励生」および「第2種奨励生」があります。出願手続の詳細については、月刊誌『武蔵美通信』4月号および通信教育課程Webサイトに募集要項を掲載してお知らせします。"
    },
    {
      "type": "heading",
      "level": 5,
      "text": "応募条件"
    },
    {
      "type": "paragraph",
      "text": "本学通信教育課程に学生として在学している者 その他、募集要項に定める通り"
    },
    {
      "type": "heading",
      "level": 5,
      "text": "募集人員"
    },
    {
      "type": "paragraph",
      "text": "15名（第1種奨励生5名・第2種奨励生10 名）"
    },
    {
      "type": "heading",
      "level": 5,
      "text": "贈与金額"
    },
    {
      "type": "list",
      "style": "unordered",
      "items": [
        "［第1種奨励生］1年間の授業料の全額",
        "［第2種奨励生］1年間の授業料の半額"
      ]
    },
    {
      "type": "heading",
      "level": 5,
      "text": "選考方法"
    },
    {
      "type": "paragraph",
      "text": "通信教育課程教務委員会において、人物・能力および学業成績を審査、その結果に基づき学長が決定します。"
    },
    {
      "type": "heading",
      "level": 4,
      "text": "日本学生支援機構奨学金"
    },
    {
      "type": "paragraph",
      "text": "独立行政法人日本学生支援機構は、日本育英会の奨学金事業が移管された機関です。憲法、教育基本法に定める「教育の機会均等」の理念のもと、経済的理由で修学が困難な優れた学生等に学資の貸与および給付を行っています。"
    },
    {
      "type": "heading",
      "level": 5,
      "text": "①日本学生支援機構 給付型奨学金"
    },
    {
      "type": "paragraph",
      "text": "原則として「返済不要」の奨学金です。採用された場合、審査のうえ決定される「区分」によって給付額が決まります。出願資格は「独立行政法人日本学生支援機構法」により定められた規定によります。給付奨学金に採用された学生については、高等教育の修学支援新制度に則って授業料等減免支援を受けることができます。詳細につきましては、通信教育課程Webサイト、月刊誌『武蔵美通信』でお知らせします。"
    },
    {
      "type": "heading",
      "level": 5,
      "text": "②日本学生支援機構 貸与型奨学金"
    },
    {
      "type": "paragraph",
      "text": "卒業後に返還するかたちの奨学金です。当該年度の夏期・冬期スクーリングを受講する学生に対し、選考のうえ、年1回貸与申請をすることができます。出願資格は「独立行政法人日本学生支援機構法」により定められた規定によります。なお、貸与型奨学金には、無利子貸与の［第1種］と、有利子（上限3％）貸与の［第2種］があります。詳細につきましては、通信教育課程Webサイト、月刊誌『武蔵美通信』でお知らせします。"
    },
    {
      "type": "heading",
      "level": 5,
      "text": "高等教育の修学支援新制度"
    },
    {
      "type": "paragraph",
      "text": "2020年4月から始まった制度で、『日本学生支援機構 給付型奨学金』と『授業料等減免制度』を組み合わせた内容となっています。本学はこの制度の対象校として選定されています。授業料等減免制度については、対象となった学生の日本学生支援機構 給付奨学金の区分に応じて、入学金・授業等の一部が減免されます。"
    },
    {
      "type": "heading",
      "level": 4,
      "text": "武蔵野美術大学校友会奨学金"
    },
    {
      "type": "heading",
      "level": 5,
      "text": "応募条件"
    },
    {
      "type": "list",
      "style": "ordered",
      "items": [
        "卒業申請書をすでに提出していること",
        "108単位以上をすでに修得していること"
      ]
    },
    {
      "type": "heading",
      "level": 5,
      "text": "出願方法"
    },
    {
      "type": "paragraph",
      "text": "出願書類一式を請求し、提出期限内に所定の書類を提出してください。詳細については、月刊誌『武蔵美通信』7+8月号に掲載予定です。"
    },
    {
      "type": "heading",
      "level": 5,
      "text": "贈与金額"
    },
    {
      "type": "paragraph",
      "text": "100,000円（3名）"
    },
    {
      "type": "heading",
      "level": 5,
      "text": "選考基準"
    },
    {
      "type": "paragraph",
      "text": "卒業制作企画案、人物、学業成績など。"
    },
    {
      "type": "list",
      "style": "unordered",
      "items": [
        "武蔵野美術大学校友会奨学金へのお問い合わせはこちら"
      ]
    },
    {
      "type": "heading",
      "level": 2,
      "text": "美術館・図書館"
    },
    {
      "type": "paragraph",
      "text": "通信教育課程の学生も美術館・図書館を利用することができます。詳細については、下記URLを参照してください。"
    },
    {
      "type": "paragraph",
      "text": "武蔵野美術大学 美術館・図書館"
    },
    {
      "type": "list",
      "style": "unordered",
      "items": [
        "https://mauml.musabi.ac.jp/"
      ]
    },
    {
      "type": "heading",
      "level": 2,
      "text": "厚生施設"
    },
    {
      "type": "heading",
      "level": 3,
      "text": "厚生施設の利用手続き"
    },
    {
      "type": "paragraph",
      "text": "本学の学生は、下記の厚生施設を利用できます。申し込み方法・受付窓口などの詳細は、通学課程のWebサイト厚生施設のページまたは総務チーム（e-mail:soumu_reserve@musabi.ac.jp）に確認してください。"
    },
    {
      "type": "list",
      "style": "unordered",
      "items": [
        "通学Webサイト「厚生施設の利用」"
      ]
    },
    {
      "type": "paragraph",
      "text": "厚生施設の利用申込みは、利用開始日の2か月前から受付けます。申込み方法は次のとおりです。"
    },
    {
      "type": "list",
      "style": "ordered",
      "items": [
        "総務チームにメールで空室状況を確認、仮予約をします。",
        "メールにて本申込フォームをお送りします。",
        "銀行振込により利用料金を納入してください。",
        "支払の確認後、申込完了メールをお送りします。",
        "宿泊当日、本人確認書類を管理人に提出してください。"
      ]
    },
    {
      "type": "list",
      "style": "unordered",
      "items": [
        "利用開始日の10日前までに申し込み手続きを完了する必要があります。",
        "厚生施設「奈良寮」「無名舎」の概観写真が、キャンパスガイドで見られます。",
        "厚生施設は、メンテナンスや工事により、開設期間であっても利用できない場合があります。"
      ]
    },
    {
      "type": "heading",
      "level": 3,
      "text": "武蔵野美術大学奈良寮"
    },
    {
      "type": "paragraph",
      "text": "奈良寮は、古美術研究旅行のための宿舎として、昭和58年7月に開設されました。 建物は、国宝・重文仏像の修復に力をそそがれた日本美術院の新納忠之介氏の旧宅で、昭和63年には、大和棟造民家本来の姿に復元されました。"
    },
    {
      "type": "paragraph",
      "text": "寮は、奈良市内で東大寺に近く、大仏殿に徒歩10分ぐらいの所にあります。東大寺の二月堂、三月堂や戒壇院あるいは奈良博物館にも近く、また足を伸ばせば、奈良公園、春日大社や新薬師寺を訪れることができます。"
    },
    {
      "type": "heading",
      "level": 4,
      "text": "住所・アクセスなど"
    },
    {
      "type": "paragraph",
      "text": "所在地：〒630-8211 奈良県奈良市雑司町59-1 電話：0742-26-6889 交通アクセス：近鉄奈良駅よりタクシー約10分 収容人員：35名 施設：食堂、浴室など 奈良寮は続き部屋となっており、各部屋に鍵がありません。 宿泊費：1人1泊2,200円 食費：夕食1,320円、朝食550円 開設期間：通年（年末年始および主に水・木は休寮）"
    },
    {
      "type": "list",
      "style": "unordered",
      "items": [
        "上記以外にも閉寮日を設けることがあります。",
        "研究室単位で行われる古美術研究旅行、通信教育課程スクーリングなどの学事実施時には、個人利用はできません。"
      ]
    },
    {
      "type": "heading",
      "level": 3,
      "text": "武蔵野美術大学五箇山「無名舎」"
    },
    {
      "type": "paragraph",
      "text": "「無名舎」（明治初年ごろ建造・合掌造・建坪約30坪）は、岐阜県白川郷とともに合掌造民家を生み出した地として有名な五箇山地方にあります。"
    },
    {
      "type": "paragraph",
      "text": "この合掌造という民家建築は、昭和40年代初頭頃、国指定の重要文化財として保存されている一部を除いて、ほとんど取り壊されようとしていました。そうした中で、本学教職員を中心とした民芸研究グループ、「無名会」の人たちが、その建築的・美的価値の保存と自然活用を目的として、居住者移転によって取り壊されようとしていた「無名舎」を買い取りました。"
    },
    {
      "type": "paragraph",
      "text": "そして自らの研究会の場として活用しながら、民家保存という実践的学習をとおして建物の維持を図ってきましたが、平成元年以降、本学がその運営を引き継いでいます。学生のみなさんもぜひ「無名舎」を訪れ、この特色ある民家建築のたたずまいを堪能してください。"
    },
    {
      "type": "paragraph",
      "text": "また、五箇山地方には、古くから伝わる民俗・民芸の数々もありますので、そちらも存分に楽しんでください。"
    },
    {
      "type": "heading",
      "level": 4,
      "text": "住所・アクセスなど"
    },
    {
      "type": "paragraph",
      "text": "所在地：〒939-1924 富山県南砺市中畑245 電話：0763-66-2957 交通アクセス：北陸新幹線新高岡駅よりJR城端線城端駅下車、タクシー約20分 収容人員：20名 施設：建物（合掌造3階建） 1階＝8畳2室、土間、台所、洗面所、浴室 2階＝14畳1室、8畳1室 別棟＝便所、洗濯場 備品（寝具20組、炊事用具、食器、冷蔵庫、掃除機、洗濯機） 利用料金：1人1泊 1,760円（食事は自炊となります） 開設期間：5月〜11月"
    },
    {
      "type": "heading",
      "level": 4,
      "text": "管理・運営の注意"
    },
    {
      "type": "paragraph",
      "text": "利用申し込みの際に現地管理人との連絡係を委嘱しますので、滞在中は責任をもって管理（鍵・火元責任）にあたってください。"
    },
    {
      "type": "heading",
      "level": 2,
      "text": "学割"
    },
    {
      "type": "heading",
      "level": 3,
      "text": "学校学生生徒旅客運賃割引証"
    },
    {
      "type": "heading",
      "level": 4,
      "text": "適用範囲"
    },
    {
      "type": "list",
      "style": "ordered",
      "items": [
        "本学の学生がスクーリング受講・科目試験受験、または卒業制作指導・卒業制作講評の受講などの学事に出席するために、片道101km以上あるJRの区間を利用する場合に、学割（学校学生生徒旅客運賃割引証）を発行します。",
        "JRの駅窓口で乗車券を購入するとき、学割を使用すると、JRの特急料金などを除き、普通運賃のみが2割引になります。",
        "JR以外は使えません。",
        "科目等履修生には発行できません。"
      ]
    },
    {
      "type": "heading",
      "level": 4,
      "text": "申し込み方法"
    },
    {
      "type": "list",
      "style": "ordered",
      "items": [
        "『諸届諸願・各種様式集』に綴じ込まれている「学校学生生徒旅客運賃割引証交付願」に必要事項を記入のうえ、110円切手を貼付し表面に宛名を明記した返送用封筒と学生証両面のコピーを添えて、通信教育チーム宛（封筒の表に「学割発行願在中」と明記すること）に申込んでください。学生証のコピーがない場合は、学割の発行はできません。",
        "「学校学生生徒旅客運賃割引証交付願」は学割発行枚数と同じ枚数が必要です。したがって、往復券を購入する場合は、交付願は1枚でよいですが、往路・復路別々に購入する場合は交付願も2枚必要になります。（JRの規則で乗車距離より乗車券の有効期間が決められていますので、乗車券購入の際には注意してください。スクーリング期間などが乗車券の有効期間を超える場合は、往路・復路の乗車券を別々に購入する必要があります。）申込用紙が不足する場合は、コピーして使用するか学校学生生徒旅客運賃割引証交付願PDFダウンロードあるいは学生ハンドブック「I-9 諸届諸願の様式」にしたがって作成してください。",
        "学割の交付にあたっては、スクーリングの場合は受講確定後に、また、科目試験の場合は申込期間終了後に発送します。ほかの学事についても出席の確認がとれてからの発送となります。"
      ]
    },
    {
      "type": "heading",
      "level": 4,
      "text": "有効期間"
    },
    {
      "type": "paragraph",
      "text": "学割の有効期間は、スクーリングまたは科目試験日などの初日の10日前から終了日の5日後までです。"
    },
    {
      "type": "heading",
      "level": 4,
      "text": "使用上の注意"
    },
    {
      "type": "paragraph",
      "text": "下記の場合は学割は無効となりますので、注意してください。"
    },
    {
      "type": "list",
      "style": "unordered",
      "items": [
        "発行記載事項を無断で訂正した場合",
        "許可を受けた者以外が使用した場合",
        "有効期間以外に使用した場合",
        "JRの規則などに違反した場合"
      ]
    },
    {
      "type": "paragraph",
      "text": "乗車券購入時および乗車時には必ず学生証を携帯してください。"
    },
    {
      "type": "heading",
      "level": 3,
      "text": "通学定期券の購入"
    },
    {
      "type": "paragraph",
      "text": "学生割引の通学定期券を購入するために必要となる「通学証明書」を発行します。 ただし、この証明書の発行と使用期間は、主には夏期スクーリングなどの長期間受講に限られます。また、各期スクーリングの受講確定後の発行となるため、1箇月間の証明書のみとなります。 なお、科目等履修生には発行できません。"
    },
    {
      "type": "heading",
      "level": 4,
      "text": "申し込み方法"
    },
    {
      "type": "paragraph",
      "text": "通学証明書の交付を希望する場合は、下記の3点を通信教育チームへ送付してください。"
    },
    {
      "type": "heading",
      "level": 4,
      "text": "注意事項"
    },
    {
      "type": "paragraph",
      "text": "● 通学定期券を購入する際、「通学証明書」は必須書類です。学生証と併せて持参してください。 ● JR・私鉄・地下鉄などにまたがる区間で通学定期券を購入する場合、「通学証明書」が複数枚必要となる場合があります。 「通学証明書」が各路線ごとに必要かどうかについては、最寄りの駅に確認してください。 ● 「学割証」の発行も併せて希望する場合は、返送用封筒を2通同封してください。 ● 「通学証明書」に記入する通学者の居住地（記入例の※2）は、スクーリング時に居住している住所になりますので、 夏期スクーリング通学時の居住地が確定してから申込んでください。 ● バスの「通学定期券」を購入する場合も、「通学証明書」が必要です。"
    },
    {
      "type": "list",
      "style": "unordered",
      "items": [
        "「通学証明書」（PDF）",
        "「通学証明書」記入例（PDF）"
      ]
    },
    {
      "type": "heading",
      "level": 3,
      "text": "優待販売プログラム"
    },
    {
      "type": "heading",
      "level": 4,
      "text": "Adobe社製品"
    },
    {
      "type": "paragraph",
      "text": "本学の学生は、本学発行の学生証の提出にてAdobe社製品の「学生・教職員個人版」を購入することができます。購入手順は次の通りです。"
    },
    {
      "type": "heading",
      "level": 5,
      "text": "購入手順"
    },
    {
      "type": "list",
      "style": "ordered",
      "items": [
        "Adobe社のWebサイトより、「学生・教職員個人版」の購入手続きを行います。「Adobe Creative Cloud学生・教職員個人向け | Adobe Creative Cloud」",
        "購入後、Adobe社より登録したメールアドレスへ資格証明書類の提出のメールが届きます。",
        "本学発行の学生証をコピーやスキャンした画像データ（表裏両面）を、Adobe社へメールにて返送してください。"
      ]
    },
    {
      "type": "list",
      "style": "unordered",
      "items": [
        "プランの契約更新時には、Adobe社より在学確認のメールが届きますので、再度Adobe社へ学生証の画像データ（表裏両面）を送付してください。"
      ]
    },
    {
      "type": "heading",
      "level": 4,
      "text": "アップル社製品"
    },
    {
      "type": "paragraph",
      "text": "アップルストア学生・教職員ストアが利用できます。 オンラインストアの利用には、UNiDAYSのアカウント作成（学生証のアップロード等による登録）が必要です。 ※ 指定校プログラムは終了しました。",
      "links": [
        {
          "text": "アップルストア学生・教職員ストア",
          "url": "https://www.apple.com/jp-edu/store"
        }
      ]
    },
    {
      "type": "heading",
      "level": 4,
      "text": "モリサワ Morisawa Fonts"
    },
    {
      "type": "paragraph",
      "text": "株式会社モリサワでは、フォントサブスクリプションサービス「Morisawa Fonts」スタンダードプランを学生向け特別価格で提供しています。 ※MORISAWA PASSPORT アカデミック版は販売を終了しました。"
    },
    {
      "type": "list",
      "style": "unordered",
      "items": [
        "Morisawa Fonts 学生向けスタンダードプラン"
      ]
    },
    {
      "type": "heading",
      "level": 4,
      "text": "ワコム社特別販売プログラム"
    },
    {
      "type": "paragraph",
      "text": "本学の学生（科目等履修生を除く）は、特別価格でペンタブレットIntuos Pro、Cintiqシリーズをご購入いただくことができます。 なお、本製品のご購入については以下の点にご注意ください。"
    },
    {
      "type": "heading",
      "level": 5,
      "text": "注意事項"
    },
    {
      "type": "list",
      "style": "unordered",
      "items": [
        "ご購入は機種を問わず1人合計2台までとさせていただきます。",
        "製品の転売および譲渡はできません。",
        "学生・教職員でない方の購入があった場合、通常版との差額をお支払いいただきます。"
      ]
    },
    {
      "type": "heading",
      "level": 5,
      "text": "購入方法"
    },
    {
      "type": "paragraph",
      "text": "Webキャンパスにログイン後、【お知らせ】を確認してください。",
      "links": [
        {
          "text": "Webキャンパス",
          "url": "https://ccap02.musabi.ac.jp/portal/action/pt/f01/Uspt010100"
        }
      ]
    },
    {
      "type": "heading",
      "level": 3,
      "text": "割引特典のある学外施設"
    },
    {
      "type": "paragraph",
      "text": "本学学生の皆さんは、一部の博物館・美術館等で割引などの特典が受けられます。 各施設の窓口で学生証を提示の上、ぜひ有効に利用してください。"
    },
    {
      "type": "paragraph",
      "text": "対象施設はこちらのページで確認してください。"
    },
    {
      "type": "list",
      "style": "unordered",
      "items": [
        "通学Webサイト「割引特典のある学外施設」"
      ]
    },
    {
      "type": "heading",
      "level": 2,
      "text": "学習会"
    },
    {
      "type": "heading",
      "level": 3,
      "text": "学習会とは"
    },
    {
      "type": "paragraph",
      "text": "学習会は、学生の自発的な呼びかけによって設立される学習と交流の場です。 学習会では、自発的に集まって学習の場を設けたり、呼び掛け合ってデッサン会を開いたり、見学会を催すことができます。同じ学科・コースの学生同士で学習会を作ったり、受講科目を同じくする学生同士で集うこともできます。"
    },
    {
      "type": "paragraph",
      "text": "地域の学生同士で学習会を作れば学科・コースを超えた情報交換の場となります。 また、インターネットを利用した学習会では全国の学生との交流が可能です。本学では、学習会設立の呼びかけが寄せられれば、その旨を月刊誌『武蔵美通信』に掲載し、全学生へ知らせます。その後の活動内容を掲載し、支援します。"
    },
    {
      "type": "paragraph",
      "text": "新しく学習会を作ろうと何人かのグループができたら、通信教育チームに学習会認定の申請手続きをしてください。大学が学習会として認定した場合、「学習会支援要項」によって活動費の一部を援助します。"
    },
    {
      "type": "paragraph",
      "text": "通信教育による学習や学生生活を充実したものにするために、積極的に呼び掛け合って学習会を起こし、参加することを勧めます。"
    },
    {
      "type": "heading",
      "level": 3,
      "text": "武蔵野美術大学造形学部通信教育課程学習会支援要項"
    },
    {
      "type": "list",
      "style": "ordered",
      "items": [
        "本通信教育課程は、学生が、自主的に学習活動を行い、相互の交流と親睦を深めるために学習会を設立しようとする場合、それを奨励し、支援する。",
        "学習会を設立しようとする場合は、2月末日までに、次の書類を通信教育課程課程長に提出して、その認定を受けるものとする学習会認定申請書（様式Ⅰ-1）学習会会員名簿（様式Ⅱ）学習会規約（様式任意）→規約例活動計画の概要を記載した書類（様式任意）→活動概要例様式I-1および様式IIは1月に配布する",
        "本通信教育課程が学習会として認定した場合には、認定書を交付する。",
        "本通信教育課程から認定を受けた学習会は、「武蔵野美術大学造形学部通信教育課程○○学習会」と称することができる。",
        "学習会の認定は当該年度単位とし、次年度も継続して認定を受けようとする場合は、次の書類を毎年2月末日までに通信教育課程課程長に提出し、継続認定を受けること。学習会継続認定申請書（様式Ⅰ-2）学習会会員名簿（様式Ⅱ）学習会規約（変更がある場合のみ提出すること。様式任意）当該年度の活動報告書（様式任意）次年度の活動計画書（様式任意）様式I-2および様式IIは1月に配布する",
        "学習会を解散する場合は、その旨文書をもって通信教育課程課程長に届け出るものとする。",
        "本通信教育課程は、認定した学習会の活動を助成するため運営費について、その一部を補助する。",
        "助成金の交付を受けようとする学習会は、次の書類を毎年2月末日までに通信教育課程課程長に提出するものとする。（様式Ⅲは毎年1月に配付する。）学習会助成金交付願（様式Ⅲ）当該年度の活動報告書（第5項で提出する場合は不要。様式任意）学習会会員名簿（第5項で提出する場合は不要。様式Ⅱ）領収書（助成金相当額分）当該年度収支明細書（2月末日現在。様式任意）",
        "助成金は、次の基準によって交付する。会員数10人以上15人まで 30,000円の限度内会員数16人以上20人まで 40,000円の限度内会員数21人以上40人まで 50,000円の限度内会員数41人以上 60,000円の限度内",
        "助成金は、毎年4月1日から翌年2月末日までに支出された学習会の運営費のうち、次の費目に対して補助する。学習会活動にかかる通信連絡費事務用消耗品費学習会活動にかかる印刷費学習会活動として使用した会場使用料など助成金の対象項目に関する詳細は、ここに定めるもののほか、別に定める。"
      ]
    },
    {
      "type": "list",
      "style": "unordered",
      "items": [
        "この要項は、平成14年4月1日から適用する。",
        "この要項は、平成25年4月1日から適用する。",
        "この要項は、令和4年4月1日から適用する。"
      ]
    },
    {
      "type": "heading",
      "level": 2,
      "text": "障害者学修支援"
    },
    {
      "type": "paragraph",
      "text": "本学通信教育課程では、「通信教育課程障害等配慮基準」、「通信教育課程面接授業実施要領」、「通信教育課程科目試験実施要領」に基づき、障害のある学生（保証人を含む）からの要望に現状で可能な限り必要な配慮、支援に取り組んでおります。"
    },
    {
      "type": "heading",
      "level": 3,
      "text": "入学前の相談"
    },
    {
      "type": "paragraph",
      "text": "入学前に心身に疾患や障がいがあり、入学後学習を進めていくうえで不安がある方は、入学・編入学の資格の「学習上の配慮を希望する方へ」を参照ください。",
      "links": [
        {
          "text": "入学・編入学の資格の「学習上の配慮を希望する方へ」",
          "url": "https://cc.musabi.ac.jp/admission-new/guide/requirement#anchor-02"
        }
      ]
    },
    {
      "type": "heading",
      "level": 3,
      "text": "入学後の相談"
    },
    {
      "type": "heading",
      "level": 4,
      "text": "配慮申請・相談の窓口"
    },
    {
      "type": "paragraph",
      "text": "通信教育チーム配慮担当 電話：042-342-3401 Eメール：cc-soudan@musabi.ac.jp",
      "links": [
        {
          "text": "042-342-3401",
          "url": "tel:042-342-3401"
        },
        {
          "text": "cc-soudan@musabi.ac.jp",
          "url": "mailto:cc-soudan@musabi.ac.jp"
        }
      ]
    },
    {
      "type": "heading",
      "level": 4,
      "text": "配慮の申請の流れ"
    },
    {
      "type": "list",
      "style": "ordered",
      "items": [
        "障害学生から通信教育チーム配慮担当へ配慮相談・申請",
        "配慮担当より障害学生へ「身体等状況連絡表」を送付",
        "「身体等状況連絡表」を記入し、配慮担当へ送付",
        "配慮担当による、支援内容の確認・調整・連絡（場合によっては面談を実施）",
        "障害等配慮専門委員会による、支援内容の確認・承認",
        "配慮担当による該当科目担当教員への配慮要請事項の伝達"
      ]
    },
    {
      "type": "heading",
      "level": 4,
      "text": "現在行っている配慮事例"
    },
    {
      "type": "list",
      "style": "unordered",
      "items": [
        "申請された配慮情報のスクーリング担当教員、保健室への共有",
        "試験会場における視覚補助器具、聴覚補助器具、治療・健康維持器具の使用の許可、座席指定",
        "階段を登ることが難しいと判断された場合、エレベーターの無い建物でのスクーリング時における低層階教室への配当",
        "車椅子使用者や公共交通機関での通学が不可能と判断された場合のスクーリング時、科目試験時における自家用車の駐車許可三鷹ルーム、市ヶ谷キャンパスは本学所有の駐車場がありませんので、近隣の有料駐車場等を使用してください。また、科目試験の地方会場では車椅子対応ができない場合があります。"
      ]
    },
    {
      "type": "paragraph",
      "text": "上記のほか、本学では合理的配慮を行いますが、障害の種類や状態により、本学への入学や個別の授業科目の受講が不可能な場合もあります。また、授業内容や評価の水準は障害の有無にかかわらず、同一となります。"
    },
    {
      "type": "heading",
      "level": 4,
      "text": "現状において対応が困難なもの"
    },
    {
      "type": "list",
      "style": "unordered",
      "items": [
        "点字化、文字の拡大、録音またはデータ化された特別な教材の提供",
        "科目試験時間等の変更、延長",
        "科目試験会場への試験時間中の介助者の入室",
        "スクーリング、科目試験等の学事での介助者（手話通訳者、ノートテイカー、移動補助者等）の確保",
        "点字、代筆等でのレポート、科目試験の答案等の提出",
        "スクーリング、科目試験等での特別な机等の使用および持込み"
      ]
    },
    {
      "type": "list",
      "style": "unordered",
      "items": [
        "このほか、配慮の希望に対し、状況によっては対応ができないことがあります。"
      ]
    },
    {
      "type": "heading",
      "level": 4,
      "text": "参考"
    },
    {
      "type": "list",
      "style": "unordered",
      "items": [
        "通信教育課程障害等配慮基準",
        "通信教育課程面接授業実施要領",
        "通信教育課程科目試験実施要領"
      ]
    },
    {
      "type": "text",
      "text": "<div class=\"p-card-list__item is-simple\">\n      <div class=\"c-card is-dark\"><a class=\"c-card__wrapper\" href=\"/koushin\">\n          <h3 class=\"c-card__title u-opacity is-inner\">教員免許状更新講習<br><span class=\"note\">対面講習と通信講習が選べる</span></h3>\n          <div class=\"c-card__image\"><img class=\"u-opacity is-inner\" src=\"https://cc.musabi.ac.jp/campus-2nd/wp-content/themes/musabi/assets/images/top/supplement_02.jpg\"></div>\n          <p class=\"c-card__button\"><span class=\"c-button is-inner\"><span>詳しく見る</span></span></p></a></div>\n    </div>"
    }
  ]
}